abx_plugin_curl/__init__.py
abx_plugin_curl/binaries.py
abx_plugin_curl/config.py
abx_plugin_curl/headers.py
abx_plugin_curl-2024.10.24.dist-info/METADATA
abx_plugin_curl-2024.10.24.dist-info/WHEEL
abx_plugin_curl-2024.10.24.dist-info/entry_points.txt
abx_plugin_curl-2024.10.24.dist-info/RECORD
